grafana_loki_client/__init__.py
grafana_loki_client/api/__init__.py
grafana_loki_client/api/build_info/__init__.py
grafana_loki_client/api/build_info/get_loki_api_v1_status_buildinfo.py
grafana_loki_client/api/format_query/__init__.py
grafana_loki_client/api/format_query/get_loki_api_v1_format_query.py
grafana_loki_client/api/format_query/post_loki_api_v1_format_query.py
grafana_loki_client/api/labels/__init__.py
grafana_loki_client/api/labels/get_loki_api_v1_labels.py
grafana_loki_client/api/query/__init__.py
grafana_loki_client/api/query/get_loki_api_v1_query.py
grafana_loki_client/api/query_range/__init__.py
grafana_loki_client/api/query_range/get_loki_api_v1_query_range.py
grafana_loki_client/api/ready/__init__.py
grafana_loki_client/api/ready/get_ready.py
grafana_loki_client/api/services/__init__.py
grafana_loki_client/api/services/get_services.py
grafana_loki_client/api/volume/__init__.py
grafana_loki_client/api/volume/get_loki_api_v1_index_volume.py
grafana_loki_client/api/volume/get_loki_api_v1_index_volume_range.py
grafana_loki_client/client.py
grafana_loki_client/errors.py
grafana_loki_client/models/__init__.py
grafana_loki_client/models/build_info_response_body.py
grafana_loki_client/models/direction.py
grafana_loki_client/models/format_query_response_body.py
grafana_loki_client/models/labels_response_body.py
grafana_loki_client/models/post_loki_api_v1_format_query_body.py
grafana_loki_client/models/query_range_response_body.py
grafana_loki_client/models/query_range_response_data.py
grafana_loki_client/models/query_range_response_data_result_type.py
grafana_loki_client/models/query_range_response_result.py
grafana_loki_client/models/query_response_body.py
grafana_loki_client/models/query_response_data.py
grafana_loki_client/models/query_response_data_result_type.py
grafana_loki_client/models/query_response_metric.py
grafana_loki_client/models/query_response_metric_level.py
grafana_loki_client/models/query_response_result.py
python_loki_clientv2-0.1.6.dist-info/LICENSE
python_loki_clientv2-0.1.6.dist-info/METADATA
python_loki_clientv2-0.1.6.dist-info/WHEEL
python_loki_clientv2-0.1.6.dist-info/RECORD
