Metadata-Version: 2.1
Name: python-loki-clientv2
Version: 0.1.6
Summary: Python client for Grafana Loki
Home-page: https://github.com/FearZee/python-loki-client
License: MIT
Author: FearZee
Author-email: Sascha.zierke+plaesh@outlook.com
Requires-Python: >=3.9,<4
Classifier: License :: OSI Approved :: MIT License
Classifier: Programming Language :: Python :: 3
Classifier: Programming Language :: Python :: 3.9
Classifier: Programming Language :: Python :: 3.10
Classifier: Programming Language :: Python :: 3.11
Classifier: Programming Language :: Python :: 3.12
Requires-Dist: attrs (>=20.1.0)
Requires-Dist: httpx (>=0.22.0)
Requires-Dist: python-dateutil (>=2.8.0)
Project-URL: Repository, https://github.com/FearZee/python-loki-client
